{
    "interactionModel": {
        "languageModel": {
            "invocationName": "luke's jokes",
            "intents": [
                {
                    "name": "AMAZON.CancelIntent",
                    "samples": []
                },
                {
                    "name": "AMAZON.HelpIntent",
                    "samples": []
                },
                {
                    "name": "AMAZON.StopIntent",
                    "samples": []
                },
                {
                    "name": "GeneralJokeIntent",
                    "samples": ["tell me a bad joke", "tell me a joke", "give me a joke"]
                },
                {
                    "name": "SpecificJokeIntent",
                    "slots": [
                        {
                            "name": "topic",
                            "type": "AMAZON.SearchQuery"
                        }
                    ],
                    "samples": [
                        "tell me a joke about {topic}",
                        "tell me a bad joke about {topic}",
                        "give me a joke about {topic}"
                    ]
                },
                {
                    "name": "AMAZON.NavigateHomeIntent",
                    "samples": []
                }
            ],
            "types": []
        }
    }
}
